ansible_flow-0.2.0.dist-info/DESCRIPTION.rst
ansible_flow-0.2.0.dist-info/METADATA
ansible_flow-0.2.0.dist-info/RECORD
ansible_flow-0.2.0.dist-info/WHEEL
ansible_flow-0.2.0.dist-info/entry_points.txt
ansible_flow-0.2.0.dist-info/metadata.json
ansible_flow-0.2.0.dist-info/top_level.txt
ansibleflow/__init__.py
ansibleflow/app.py
ansibleflow/config.py
ansibleflow/rekey.py
ansibleflow/run.py
ansibleflow/venv.py
