Metadata-Version: 2.0
Name: ansible-flow
Version: 0.2.0
Summary: Workflow tool to speed up interactions with Ansible
Home-page: https://github.com/jmvrbanac/ansible-flow
Author: John Vrbanac
Author-email: john.vrbanac@linux.com
License: Apache v2
Keywords: ansible management workflow
Platform: UNKNOWN
Classifier: Development Status :: 3 - Alpha
Classifier: Intended Audience :: Developers
Classifier: License :: OSI Approved :: Apache Software License
Classifier: Programming Language :: Python :: 2.7
Classifier: Programming Language :: Python :: 3.3
Classifier: Programming Language :: Python :: 3.4
Requires-Dist: ansible (>=2.0)
Requires-Dist: capturer
Requires-Dist: pyyaml
Requires-Dist: virtualenv
